bad_spence/__init__.py
bad_spence/fetch.py
bad_spence/generator.py
bad_spence-0.1.0.dist-info/LICENSE
bad_spence-0.1.0.dist-info/METADATA
bad_spence-0.1.0.dist-info/WHEEL
bad_spence-0.1.0.dist-info/entry_points.txt
bad_spence-0.1.0.dist-info/top_level.txt
bad_spence-0.1.0.dist-info/RECORD
