Metadata-Version: 2.1
Name: bad-spence
Version: 0.1.0
Summary: A DOI-based citation generator.
Home-page: https://github.com/davidmaamoaix/bad-spence
Author: David Ma
Author-email: davidma@davidma.cn
License: MIT
License-File: LICENSE
Requires-Dist: requests
Requires-Dist: pqdm
